transformer_engine_build_tools_tmp2/VERSION
transformer_engine_build_tools_tmp2/__init__.py
transformer_engine_build_tools_tmp2/te_version.py
transformer_engine_build_tools_tmp2/build_tools/__init__.py
transformer_engine_build_tools_tmp2/build_tools/build_ext.py
transformer_engine_build_tools_tmp2/build_tools/utils.py
transformer_engine_build_tools_tmp2/common/common.h
transformer_engine_build_tools_tmp2/common/nvtx.h
transformer_engine_build_tools_tmp2/common/util/cast.cu
transformer_engine_build_tools_tmp2/common/util/cuda_driver.cpp
transformer_engine_build_tools_tmp2/common/util/cuda_driver.h
transformer_engine_build_tools_tmp2/common/util/cuda_runtime.cpp
transformer_engine_build_tools_tmp2/common/util/cuda_runtime.h
transformer_engine_build_tools_tmp2/common/util/logging.h
transformer_engine_build_tools_tmp2/common/util/math.h
transformer_engine_build_tools_tmp2/common/util/rtc.cpp
transformer_engine_build_tools_tmp2/common/util/rtc.h
transformer_engine_build_tools_tmp2/common/util/string.h
transformer_engine_build_tools_tmp2/common/util/string_header.h.in
transformer_engine_build_tools_tmp2/common/util/system.cpp
transformer_engine_build_tools_tmp2/common/util/system.h
transformer_engine_build_tools_tmp2/common/util/vectorized_pointwise.h
transformer_engine_build_tools_tmp2/cudnn-frontend/.clang-format
transformer_engine_build_tools_tmp2/cudnn-frontend/.git
transformer_engine_build_tools_tmp2/cudnn-frontend/CMakeLists.txt
transformer_engine_build_tools_tmp2/cudnn-frontend/CONTRIBUTING.md
transformer_engine_build_tools_tmp2/cudnn-frontend/LICENSE.txt
transformer_engine_build_tools_tmp2/cudnn-frontend/README.FE.0.x.md
transformer_engine_build_tools_tmp2/cudnn-frontend/README.FE.1.0.md
transformer_engine_build_tools_tmp2/cudnn-frontend/README.md
transformer_engine_build_tools_tmp2/cudnn-frontend/pyproject.toml
transformer_engine_build_tools_tmp2/cudnn-frontend/requirements.txt
transformer_engine_build_tools_tmp2/cudnn-frontend/setup.py
transformer_engine_build_tools_tmp2-1.7.0.dev0.dist-info/LICENSE
transformer_engine_build_tools_tmp2-1.7.0.dev0.dist-info/METADATA
transformer_engine_build_tools_tmp2-1.7.0.dev0.dist-info/WHEEL
transformer_engine_build_tools_tmp2-1.7.0.dev0.dist-info/top_level.txt
transformer_engine_build_tools_tmp2-1.7.0.dev0.dist-info/RECORD
