Metadata-Version: 2.1
Name: transformer-engine-build-tools-tmp2
Version: 1.7.0.dev0
Summary: Transformer acceleration library - Build Requirements
License-File: LICENSE
